hacs_cli/__init__.py
hacs_cli/__main__.py
hacs_cli-0.4.3.dist-info/METADATA
hacs_cli-0.4.3.dist-info/WHEEL
hacs_cli-0.4.3.dist-info/entry_points.txt
hacs_cli-0.4.3.dist-info/RECORD
